rqalpha/VERSION.txt
rqalpha/__init__.py
rqalpha/__main__.py
rqalpha/cache_control.py
rqalpha/config.yml
rqalpha/const.py
rqalpha/environment.py
rqalpha/event_bus.py
rqalpha/events.py
rqalpha/execution_context.py
rqalpha/interface.py
rqalpha/main.py
rqalpha/plot.py
rqalpha/user_module.py
rqalpha/analyser/__init__.py
rqalpha/analyser/risk.py
rqalpha/analyser/risk_cal.py
rqalpha/api/__init__.py
rqalpha/api/api_base.py
rqalpha/api/api_future.py
rqalpha/api/api_stock.py
rqalpha/api/ext.py
rqalpha/api/helper.py
rqalpha/api/names.py
rqalpha/core/__init__.py
rqalpha/core/default_broker.py
rqalpha/core/default_event_source.py
rqalpha/core/default_matcher.py
rqalpha/core/default_strategy_loader.py
rqalpha/core/strategy.py
rqalpha/core/strategy_universe.py
rqalpha/data/__init__.py
rqalpha/data/base_data_source.py
rqalpha/data/converter.py
rqalpha/data/data_proxy.py
rqalpha/data/date_set.py
rqalpha/data/daybar_store.py
rqalpha/data/dividend_store.py
rqalpha/data/instrument_mixin.py
rqalpha/data/instrument_store.py
rqalpha/data/risk_free_helper.py
rqalpha/data/trading_dates_mixin.py
rqalpha/data/trading_dates_store.py
rqalpha/data/yield_curve_store.py
rqalpha/mod/__init__.py
rqalpha/mod/mod_handler.py
rqalpha/mod/progress/__init__.py
rqalpha/model/__init__.py
rqalpha/model/bar.py
rqalpha/model/commission.py
rqalpha/model/dividend.py
rqalpha/model/instrument.py
rqalpha/model/margin.py
rqalpha/model/order.py
rqalpha/model/slippage.py
rqalpha/model/snapshot.py
rqalpha/model/tax.py
rqalpha/model/trade.py
rqalpha/model/portfolio/__init__.py
rqalpha/model/portfolio/base_portfolio.py
rqalpha/model/portfolio/future_portfolio.py
rqalpha/model/portfolio/stock_portfolio.py
rqalpha/model/position/__init__.py
rqalpha/model/position/base_position.py
rqalpha/model/position/future_position.py
rqalpha/model/position/stock_position.py
rqalpha/proxy/__init__.py
rqalpha/resource/__init__.py
rqalpha/resource/ricequant-logo.png
rqalpha-0.3.0.dist-info/DESCRIPTION.rst
rqalpha-0.3.0.dist-info/METADATA
rqalpha-0.3.0.dist-info/RECORD
rqalpha-0.3.0.dist-info/WHEEL
rqalpha-0.3.0.dist-info/entry_points.txt
rqalpha-0.3.0.dist-info/metadata.json
rqalpha-0.3.0.dist-info/top_level.txt
