Metadata-Version: 2.0
Name: rqalpha
Version: 0.3.0
Summary: Ricequant Algorithm Trading System
Home-page: https://github.com/ricequant/rqalpha
Author: ricequant
Author-email: public@ricequant.com
License: UNKNOWN
Platform: UNKNOWN
Requires-Dist: PyYAML (>=3.12)
Requires-Dist: SQLAlchemy
Requires-Dist: XlsxWriter (>=0.9.6)
Requires-Dist: attrdict (>=2.0.0)
Requires-Dist: bcolz (==1.1.0)
Requires-Dist: click (>=6.6)
Requires-Dist: dill (==0.2.5)
Requires-Dist: enum34 (>=1.1.6)
Requires-Dist: jsonpickle (==0.9.4)
Requires-Dist: line-profiler (==1.0)
Requires-Dist: logbook (==1.0.0)
Requires-Dist: matplotlib (>=1.5.1)
Requires-Dist: numpy (>=1.11.1)
Requires-Dist: pandas (>=0.18.1)
Requires-Dist: protobuf (>=3.0.0b3)
Requires-Dist: pytest (>=2.9.2)
Requires-Dist: python-dateutil (>=2.5.3)
Requires-Dist: pytz (>=2016.4)
Requires-Dist: raven (==5.27.1)
Requires-Dist: redis
Requires-Dist: requests (>=2.11.1)
Requires-Dist: simplejson (>=3.10.0)
Requires-Dist: six (>=1.10.0)
Requires-Dist: typing (>=3.5.2.2)
